rnae/__init__.py
rnae/data.py
rnae/rnae.py
rnae/dados/diagnostico.csv
rnae/dados/iris.csv
rnae-1.0.1.dist-info/METADATA
rnae-1.0.1.dist-info/WHEEL
rnae-1.0.1.dist-info/top_level.txt
rnae-1.0.1.dist-info/RECORD
