Metadata-Version: 2.1
Name: rnae
Version: 1.0.1
Summary: Rede Neural Artifical Evolucionária
Home-page: https://bitbucket.org/PereiraSomoza/rnae
Author: Eduardo S. Pereira
Author-email: pereira.somoza@gmail.com
License: Apache License 2.0
Platform: UNKNOWN
Requires-Dist: numpy
Requires-Dist: pygenec
